signs/__init__.py
signs/commands/__init__.py
signs/commands/autoprep.py
signs/commands/clean.py
signs/commands/describe.py
signs/commands/docsimilarity.py
signs/commands/embeds.py
signs/commands/load_vectors.py
signs/commands/preds.py
signs/commands/stopwords.py
signs/commands/transform.py
signs/commands/verbatims.py
signs/grams/__init__.py
signs/grams/grams.py
signs/models/__init__.py
signs/models/mlp.py
signs/preprocess/__init__.py
signs/preprocess/embedding_index.py
signs/preprocess/embedding_matrix.py
signs/preprocess/tokenize.py
signs/preprocess/transforms.py
signs/similarity/__init__.py
signs/similarity/doc_similarity.py
signs/similarity/similarity.py
signs/utils/__init__.py
signs/utils/converters.py
signs/utils/file.py
signs/utils/html_print.py
signs/utils/stopwords.py
signs/vectorize/__init__.py
signs/vectorize/gensim_doc2vec_train.py
signs/vectorize/spacy.py
signs-0.3.1.dist-info/LICENSE
signs-0.3.1.dist-info/METADATA
signs-0.3.1.dist-info/WHEEL
signs-0.3.1.dist-info/top_level.txt
signs-0.3.1.dist-info/RECORD
