Metadata-Version: 2.1
Name: signs
Version: 0.3.1
Summary: Signs Text Processing for Deep Learning
Home-page: http://autonom.io
Author: Mikko Kotila
Author-email: mailme@mikkokotila.com
Maintainer: Mikko Kotila
Maintainer-email: mailme@mikkokotila.com
License: MIT
Download-URL: https://github.com/autonomio/signs/
Platform: UNKNOWN
Classifier: Intended Audience :: Science/Research
Classifier: Programming Language :: Python :: 3.6
Classifier: License :: OSI Approved :: MIT License
Classifier: Topic :: Scientific/Engineering :: Human Machine Interfaces
Classifier: Topic :: Scientific/Engineering :: Artificial Intelligence
Classifier: Topic :: Scientific/Engineering :: Mathematics
Classifier: Operating System :: POSIX
Classifier: Operating System :: Unix
Classifier: Operating System :: MacOS
Requires-Dist: kerasplotlib
Requires-Dist: wrangle
Requires-Dist: pandas
Requires-Dist: numpy
Requires-Dist: cython
Requires-Dist: spacy
Requires-Dist: gensim
Requires-Dist: keras
Requires-Dist: ipython
